.coveragerc
AUTHORS
CHANGES
COPYING
MANIFEST.in
README.rst
run-coverage.sh
setup.cfg
setup.py
docs/Makefile
docs/conf.py
docs/index.rst
docs/_templates/sidebarintro.html
docs/_themes/README
docs/_themes/flask_theme_support.py
docs/_themes/flask/layout.html
docs/_themes/flask/relations.html
docs/_themes/flask/theme.conf
docs/_themes/flask/static/flasky.css_t
docs/_themes/flask_small/layout.html
docs/_themes/flask_small/theme.conf
docs/_themes/flask_small/static/flasky.css_t
setuptools_bower/__init__.py
setuptools_bower/setuptools_command.py
setuptools_bower/version.py
setuptools_bower.egg-info/PKG-INFO
setuptools_bower.egg-info/SOURCES.txt
setuptools_bower.egg-info/dependency_links.txt
setuptools_bower.egg-info/entry_points.txt
setuptools_bower.egg-info/not-zip-safe
setuptools_bower.egg-info/requires.txt
setuptools_bower.egg-info/top_level.txt
tests/__init__.py
tests/test_install_bower.py