Metadata-Version: 1.1
Name: setuptools-bower
Version: 0.2.0
Summary: Setuptools commands for integrating bower.
Home-page: http://github.com/inveniosoftware/setuptools-bower/
Author: Invenio collaboration
Author-email: info@invenio-software.org
License: GPLv2
Platform: any
Classifier: Environment :: Web Environment
Classifier: Framework :: Setuptools Plugin
Classifier: Intended Audience :: Developers
Classifier: License :: OSI Approved :: GNU General Public License v2 (GPLv2)
Classifier: Operating System :: OS Independent
Classifier: Programming Language :: Python
Classifier: Programming Language :: Python :: 2
Classifier: Programming Language :: Python :: 2.6
Classifier: Programming Language :: Python :: 2.7
Classifier: Programming Language :: Python :: 3
Classifier: Programming Language :: Python :: 3.3
Classifier: Programming Language :: Python :: 3.4
Classifier: Development Status :: 5 - Production/Stable
